percommon/__init__.py
percommon/asgi.py
percommon/settings.py
percommon/urls.py
percommon/wsgi.py
percommon-0.1.0.dist-info/WHEEL
percommon-0.1.0.dist-info/METADATA
percommon-0.1.0.dist-info/RECORD
