Metadata-Version: 2.1
Name: percommon
Version: 0.1.0
Summary: Common modules for developering per apps
Author: Robert Townley
Author-email: me@roberttownley.com
Requires-Python: >=3.9,<4.0
Classifier: Programming Language :: Python :: 3
Classifier: Programming Language :: Python :: 3.9
Requires-Dist: Django (>=3.1.4,<4.0.0)
Requires-Dist: django-cors-headers (>=3.6.0,<4.0.0)
Requires-Dist: django-extensions (>=3.1.0,<4.0.0)
Requires-Dist: djangorestframework (>=3.12.2,<4.0.0)
Requires-Dist: psycopg2 (>=2.8.6,<3.0.0)
Requires-Dist: requests (>=2.25.0,<3.0.0)
